snappass/__init__.py
snappass/main.py
snappass/static/bootstrap/css/bootstrap-theme.css
snappass/static/bootstrap/css/bootstrap-theme.css.map
snappass/static/bootstrap/css/bootstrap-theme.min.css
snappass/static/bootstrap/css/bootstrap-theme.min.css.map
snappass/static/bootstrap/css/bootstrap.css
snappass/static/bootstrap/css/bootstrap.css.map
snappass/static/bootstrap/css/bootstrap.min.css
snappass/static/bootstrap/css/bootstrap.min.css.map
snappass/static/bootstrap/fonts/glyphicons-halflings-regular.eot
snappass/static/bootstrap/fonts/glyphicons-halflings-regular.svg
snappass/static/bootstrap/fonts/glyphicons-halflings-regular.ttf
snappass/static/bootstrap/fonts/glyphicons-halflings-regular.woff
snappass/static/bootstrap/fonts/glyphicons-halflings-regular.woff2
snappass/static/bootstrap/js/bootstrap.js
snappass/static/bootstrap/js/bootstrap.min.js
snappass/static/clipboardjs/clipboard.js
snappass/static/clipboardjs/clipboard.min.js
snappass/static/fontawesome/css/font-awesome.min.css
snappass/static/fontawesome/fonts/FontAwesome.otf
snappass/static/fontawesome/fonts/fontawesome-webfont.eot
snappass/static/fontawesome/fonts/fontawesome-webfont.svg
snappass/static/fontawesome/fonts/fontawesome-webfont.ttf
snappass/static/fontawesome/fonts/fontawesome-webfont.woff
snappass/static/fontawesome/fonts/fontawesome-webfont.woff2
snappass/static/jquery/jquery-3.6.0.min.js
snappass/static/snappass/css/custom.css
snappass/static/snappass/scripts/clipboard_button.js
snappass/static/snappass/scripts/preview.js
snappass/templates/base.html
snappass/templates/confirm.html
snappass/templates/expired.html
snappass/templates/password.html
snappass/templates/preview.html
snappass/templates/set_password.html
snappass-1.6.2.dist-info/AUTHORS.rst
snappass-1.6.2.dist-info/LICENSE
snappass-1.6.2.dist-info/METADATA
snappass-1.6.2.dist-info/WHEEL
snappass-1.6.2.dist-info/entry_points.txt
snappass-1.6.2.dist-info/top_level.txt
snappass-1.6.2.dist-info/RECORD
