Metadata-Version: 2.1
Name: snappass
Version: 1.6.2
Summary: It's like SnapChat... for Passwords.
Home-page: http://github.com/Pinterest/snappass/
Author: Dave Dash
Author-email: dd+github@davedash.com
License: MIT
Classifier: Development Status :: 5 - Production/Stable
Classifier: Intended Audience :: Developers
Classifier: Natural Language :: English
Classifier: License :: OSI Approved :: MIT License
Classifier: Operating System :: OS Independent
Classifier: Programming Language :: Python
Classifier: Programming Language :: Python :: 3
Classifier: Programming Language :: Python :: 3.8
Classifier: Programming Language :: Python :: 3.9
Classifier: Programming Language :: Python :: 3.10
Classifier: Topic :: Software Development :: Libraries :: Python Modules
Requires-Python: >=3.8, <4
License-File: LICENSE
License-File: AUTHORS.rst
Requires-Dist: Flask
Requires-Dist: redis
Requires-Dist: cryptography
